{
	"configurations" : 
	[
		{
			"directories" : 
			[
				{
					"build" : ".",
					"hasInstallRule" : true,
					"jsonFile" : "directory-.-62810a0369cd94c2b605.json",
					"minimumCMakeVersion" : 
					{
						"string" : "3.12"
					},
					"projectIndex" : 0,
					"source" : ".",
					"targetIndexes" : 
					[
						0,
						1
					]
				}
			],
			"name" : "",
			"projects" : 
			[
				{
					"directoryIndexes" : 
					[
						0
					],
					"name" : "bot_desc",
					"targetIndexes" : 
					[
						0,
						1
					]
				}
			],
			"targets" : 
			[
				{
					"directoryIndex" : 0,
					"id" : "bot_desc_uninstall::@6890427a1f51a3e7e1df",
					"jsonFile" : "target-bot_desc_uninstall-e267fa8aa9387ef74750.json",
					"name" : "bot_desc_uninstall",
					"projectIndex" : 0
				},
				{
					"directoryIndex" : 0,
					"id" : "uninstall::@6890427a1f51a3e7e1df",
					"jsonFile" : "target-uninstall-66819d0e45f647d41023.json",
					"name" : "uninstall",
					"projectIndex" : 0
				}
			]
		}
	],
	"kind" : "codemodel",
	"paths" : 
	{
		"build" : "/home/jungle/ros_cpp/chapt6_ws/build/bot_desc",
		"source" : "/home/jungle/ros_cpp/chapt6_ws/src/bot_desc"
	},
	"version" : 
	{
		"major" : 2,
		"minor" : 3
	}
}
